{
    "schemaVersion": 1,
    "id": "chunkdata",
    "version": "1.0.0",
    "name": "Chunk Data API",
    "description": "An API for reading and writing data to a chunk using its NBT",
    "authors": [
        "Carlettos"
    ],
    "contact": {
        "homepage": "",
        "sources": "https://github.com/Carlettos1/chunk-data"
    },
    "license": "CC0-1.0",
    "icon": "assets/chunkdata/icon.png",
    "environment": "*",
    "entrypoints": {
        "main": [
            "me.carlettos.chunkdata.ChunkData"
        ]
    },
    "mixins": [
        "chunkdata.mixins.json"
    ],
    "depends": {
        "fabricloader": ">=0.14.9",
        "fabric-api": "*",
        "minecraft": "~1.19",
        "java": ">=17"
    },
    "suggests": {
        "another-mod": "*"
    }
}
